README.rst
setup.py
src/gherkin_parser/__init__.py
src/gherkin_parser/__main__.py
src/gherkin_parser/exceptions.py
src/gherkin_parser/parser.py
src/gherkin_parser.egg-info/PKG-INFO
src/gherkin_parser.egg-info/SOURCES.txt
src/gherkin_parser.egg-info/dependency_links.txt
src/gherkin_parser.egg-info/requires.txt
src/gherkin_parser.egg-info/top_level.txt